{
  "objective": "time",
  "quick": false,
  "elapsed_s": 294.46723651885986,
  "archetypes": [
    {
      "key": "urban_small",
      "name": "Urbano pequeño (base Castelldefels)",
      "description": "Flota de 5 drones (2L+2M+1P) y 30 pedidos sobre los destinos reales de Castelldefels. Escenario canónico del proyecto.",
      "config": {
        "n_drones": 5,
        "n_orders": 30,
        "charger_w": 180.0,
        "wmin": 0.3,
        "wmax": 4.0,
        "n_train": 8,
        "n_test": 40,
        "mc": 200,
        "ga_pop": 24,
        "ga_gen": 16,
        "bayes": 70
      },
      "objective": "time",
      "baseline_full_makespan": 21855.665338647406,
      "baseline_partial_makespan": 19090.423075618306,
      "best_tuner": "Genético",
      "best_weights": [
        0.026779149966122375,
        0.0018124412607656893,
        0.6434264275002521,
        0.08287401480913076,
        0.245107966463729
      ],
      "stages": {
        "labels": [
          "Base (100%)",
          "Recarga parcial",
          "Parcial + Genético"
        ],
        "makespan_mean": [
          21855.665338647406,
          19090.423075618306,
          18986.166281702965
        ],
        "delivered_mean": [
          30.0,
          30.0,
          30.0
        ]
      },
      "improvement_recharge_pct": 12.65229047106298,
      "improvement_total_pct": 13.129314584947924,
      "improvement_tuning_pct": 0.5461209188626884,
      "p_value_recharge": 1.6623188566119312e-12,
      "tuners": {
        "Monte Carlo": {
          "weights": [
            0.09591330290365821,
            0.09250689294684769,
            0.3567477730522198,
            0.1265820439995597,
            0.32824998709771464
          ],
          "best_objective": 0.9948164841861817,
          "n_evaluations": 200,
          "time_improvement_pct": 0.5183515813818268
        },
        "Genético": {
          "weights": [
            0.026779149966122375,
            0.0018124412607656893,
            0.6434264275002521,
            0.08287401480913076,
            0.245107966463729
          ],
          "best_objective": 0.989720093439638,
          "n_evaluations": 260,
          "time_improvement_pct": 1.0279906560361998
        },
        "Bayesiano": {
          "weights": [
            0.07261567272820475,
            0.01642779637948788,
            0.39850315146353693,
            0.10910787148257778,
            0.4033455079461927
          ],
          "best_objective": 0.9914727990526437,
          "n_evaluations": 70,
          "time_improvement_pct": 0.8527200947356246
        }
      },
      "greedy_vs_jv": {
        "time_saving_pct": 0.048507552968975375,
        "p_value_time": 0.9091466461132967
      },
      "figures": {
        "base_vs_improved": "results\\study_v2\\urban_small\\base_vs_improved.png",
        "convergence": "results\\study_v2\\urban_small\\convergence_3tuners.png",
        "weights": "results\\study_v2\\urban_small\\weights5.png",
        "test_improvement": "results\\study_v2\\urban_small\\test_improvement.png",
        "greedy_vs_jv": "results\\study_v2\\urban_small\\greedy_vs_jv.png"
      }
    },
    {
      "key": "ecommerce_light",
      "name": "Perfil e-commerce (paquetería ligera)",
      "description": "Pedidos ligeros (0.1–1.5 kg); muchos drones ligeros son viables, lo que da más libertad al optimizador.",
      "config": {
        "n_drones": 5,
        "n_orders": 40,
        "charger_w": 180.0,
        "wmin": 0.1,
        "wmax": 1.5,
        "n_train": 8,
        "n_test": 40,
        "mc": 200,
        "ga_pop": 24,
        "ga_gen": 16,
        "bayes": 70
      },
      "objective": "time",
      "baseline_full_makespan": 9886.164345594143,
      "baseline_partial_makespan": 6748.4003180783475,
      "best_tuner": "Genético",
      "best_weights": [
        0.19956452017100115,
        0.010351940976605231,
        0.28516822887151255,
        0.19587783555576777,
        0.30903747442511326
      ],
      "stages": {
        "labels": [
          "Base (100%)",
          "Recarga parcial",
          "Parcial + Genético"
        ],
        "makespan_mean": [
          9886.164345594143,
          6748.4003180783475,
          6419.308596954108
        ],
        "delivered_mean": [
          40.0,
          40.0,
          40.0
        ]
      },
      "improvement_recharge_pct": 31.738942605320613,
      "improvement_total_pct": 35.067753553834756,
      "improvement_tuning_pct": 4.876588607860634,
      "p_value_recharge": 3.2496491614610375e-18,
      "tuners": {
        "Monte Carlo": {
          "weights": [
            0.24807650264061182,
            0.013957421060334978,
            0.3527764874283193,
            0.23605264865322687,
            0.149136940217507
          ],
          "best_objective": 0.8755186968687755,
          "n_evaluations": 200,
          "time_improvement_pct": 12.44813031312245
        },
        "Genético": {
          "weights": [
            0.19956452017100115,
            0.010351940976605231,
            0.28516822887151255,
            0.19587783555576777,
            0.30903747442511326
          ],
          "best_objective": 0.8496451357695973,
          "n_evaluations": 242,
          "time_improvement_pct": 15.03548642304027
        },
        "Bayesiano": {
          "weights": [
            0.26626921015451926,
            0.0028569128461490615,
            0.37767074561205854,
            0.16538502223529783,
            0.18781810915197533
          ],
          "best_objective": 0.8710116001447701,
          "n_evaluations": 70,
          "time_improvement_pct": 12.898839985522992
        }
      },
      "greedy_vs_jv": {
        "time_saving_pct": 0.7154658634858727,
        "p_value_time": 0.6760386658515585
      },
      "figures": {
        "base_vs_improved": "results\\study_v2\\ecommerce_light\\base_vs_improved.png",
        "convergence": "results\\study_v2\\ecommerce_light\\convergence_3tuners.png",
        "weights": "results\\study_v2\\ecommerce_light\\weights5.png",
        "test_improvement": "results\\study_v2\\ecommerce_light\\test_improvement.png",
        "greedy_vs_jv": "results\\study_v2\\ecommerce_light\\greedy_vs_jv.png"
      }
    },
    {
      "key": "industrial_heavy",
      "name": "Perfil industrial (carga pesada)",
      "description": "Pedidos pesados (1.5–4.0 kg) que solo sirven medios y pesados; problema muy restringido por carga útil.",
      "config": {
        "n_drones": 5,
        "n_orders": 40,
        "charger_w": 180.0,
        "wmin": 1.5,
        "wmax": 4.0,
        "n_train": 8,
        "n_test": 40,
        "mc": 200,
        "ga_pop": 24,
        "ga_gen": 16,
        "bayes": 70
      },
      "objective": "time",
      "baseline_full_makespan": 47331.681114018626,
      "baseline_partial_makespan": 44152.78796646573,
      "best_tuner": "Monte Carlo",
      "best_weights": [
        0.002360368273641967,
        0.3250358916384606,
        0.21472685300008074,
        0.1821712239711514,
        0.27570566311666533
      ],
      "stages": {
        "labels": [
          "Base (100%)",
          "Recarga parcial",
          "Parcial + Monte Carlo"
        ],
        "makespan_mean": [
          47331.681114018626,
          44152.78796646573,
          44141.12661249747
        ],
        "delivered_mean": [
          40.0,
          40.0,
          40.0
        ]
      },
      "improvement_recharge_pct": 6.716205874655433,
      "improvement_total_pct": 6.740843397967075,
      "improvement_tuning_pct": 0.026411364956422094,
      "p_value_recharge": 2.2527282174342245e-14,
      "tuners": {
        "Monte Carlo": {
          "weights": [
            0.002360368273641967,
            0.3250358916384606,
            0.21472685300008074,
            0.1821712239711514,
            0.27570566311666533
          ],
          "best_objective": 0.9975272421920374,
          "n_evaluations": 200,
          "time_improvement_pct": 0.24727578079626325
        },
        "Genético": {
          "weights": [
            0.005915438712287567,
            0.3921358070438461,
            0.3036336486466544,
            0.21519855059193305,
            0.083116555005279
          ],
          "best_objective": 0.9975272421920374,
          "n_evaluations": 257,
          "time_improvement_pct": 0.24727578079626325
        },
        "Bayesiano": {
          "weights": [
            0.0017756984776513723,
            0.3159800850345862,
            0.21983009749727478,
            0.023194415111016983,
            0.4392197038794707
          ],
          "best_objective": 0.9975272421920374,
          "n_evaluations": 70,
          "time_improvement_pct": 0.24727578079626325
        }
      },
      "greedy_vs_jv": {
        "time_saving_pct": -0.267564550807354,
        "p_value_time": 0.000771594576032268
      },
      "figures": {
        "base_vs_improved": "results\\study_v2\\industrial_heavy\\base_vs_improved.png",
        "convergence": "results\\study_v2\\industrial_heavy\\convergence_3tuners.png",
        "weights": "results\\study_v2\\industrial_heavy\\weights5.png",
        "test_improvement": "results\\study_v2\\industrial_heavy\\test_improvement.png",
        "greedy_vs_jv": "results\\study_v2\\industrial_heavy\\greedy_vs_jv.png"
      }
    },
    {
      "key": "operational_day",
      "name": "Día operativo (10 drones, 150 pedidos)",
      "description": "Jornada con 10 drones y 150 pedidos (~15/dron); múltiples ciclos de recarga donde el reparto de carga influye en el makespan.",
      "config": {
        "n_drones": 10,
        "n_orders": 150,
        "charger_w": 300.0,
        "wmin": 0.3,
        "wmax": 4.0,
        "n_train": 5,
        "n_test": 14,
        "mc": 90,
        "ga_pop": 16,
        "ga_gen": 10,
        "bayes": 40
      },
      "objective": "time",
      "baseline_full_makespan": 44725.04920454053,
      "baseline_partial_makespan": 42379.80652215214,
      "best_tuner": "Genético",
      "best_weights": [
        0.03389140826405886,
        0.6181675245433347,
        0.3479410671926064,
        0.0,
        0.0
      ],
      "stages": {
        "labels": [
          "Base (100%)",
          "Recarga parcial",
          "Parcial + Genético"
        ],
        "makespan_mean": [
          44725.04920454053,
          42379.80652215214,
          42379.62514931266
        ],
        "delivered_mean": [
          150.0,
          150.0,
          150.0
        ]
      },
      "improvement_recharge_pct": 5.243689440480935,
      "improvement_total_pct": 5.244094969021883,
      "improvement_tuning_pct": 0.0004279699563575354,
      "p_value_recharge": 3.310095749856024e-05,
      "tuners": {
        "Monte Carlo": {
          "weights": [
            0.016655887124424153,
            0.25384513930985136,
            0.24519192541143658,
            0.28357476526624525,
            0.20073228288804265
          ],
          "best_objective": 0.989628551455563,
          "n_evaluations": 90,
          "time_improvement_pct": 1.037144854443698
        },
        "Genético": {
          "weights": [
            0.03389140826405886,
            0.6181675245433347,
            0.3479410671926064,
            0.0,
            0.0
          ],
          "best_objective": 0.9883349158184115,
          "n_evaluations": 70,
          "time_improvement_pct": 1.1665084181588496
        },
        "Bayesiano": {
          "weights": [
            0.2257603921965453,
            0.18852369761848098,
            0.36406974336260034,
            0.13404613858823403,
            0.08760002823413943
          ],
          "best_objective": 0.9888158790668155,
          "n_evaluations": 40,
          "time_improvement_pct": 1.1184120933184596
        }
      },
      "greedy_vs_jv": {
        "time_saving_pct": -0.7486748539105007,
        "p_value_time": 0.055236748215966296
      },
      "figures": {
        "base_vs_improved": "results\\study_v2\\operational_day\\base_vs_improved.png",
        "convergence": "results\\study_v2\\operational_day\\convergence_3tuners.png",
        "weights": "results\\study_v2\\operational_day\\weights5.png",
        "test_improvement": "results\\study_v2\\operational_day\\test_improvement.png",
        "greedy_vs_jv": "results\\study_v2\\operational_day\\greedy_vs_jv.png"
      }
    },
    {
      "key": "massive_ops",
      "name": "Operación masiva (25 drones, 600 pedidos)",
      "description": "Gran escala: 25 drones y 600 pedidos. Prueba la robustez cuando cada evaluación es costosa.",
      "config": {
        "n_drones": 25,
        "n_orders": 600,
        "charger_w": 300.0,
        "wmin": 0.3,
        "wmax": 4.0,
        "n_train": 3,
        "n_test": 8,
        "mc": 90,
        "ga_pop": 16,
        "ga_gen": 10,
        "bayes": 40
      },
      "objective": "time",
      "baseline_full_makespan": 74801.45323205675,
      "baseline_partial_makespan": 72991.93082989358,
      "best_tuner": "Genético",
      "best_weights": [
        0.10376528441063089,
        0.17090795287526034,
        0.21261268356748492,
        0.2402963749837852,
        0.2724177041628385
      ],
      "stages": {
        "labels": [
          "Base (100%)",
          "Recarga parcial",
          "Parcial + Genético"
        ],
        "makespan_mean": [
          74801.45323205675,
          72991.93082989358,
          72323.38737968414
        ],
        "delivered_mean": [
          600.0,
          600.0,
          600.0
        ]
      },
      "improvement_recharge_pct": 2.4191005976173843,
      "improvement_total_pct": 3.3128578995449534,
      "improvement_tuning_pct": 0.915914187511318,
      "p_value_recharge": 0.011063589742355136,
      "tuners": {
        "Monte Carlo": {
          "weights": [
            0.11165957070198497,
            0.15915994967430686,
            0.2726477089004232,
            0.23836162196710645,
            0.21817114875617857
          ],
          "best_objective": 0.9847709523236958,
          "n_evaluations": 90,
          "time_improvement_pct": 1.5229047676304166
        },
        "Genético": {
          "weights": [
            0.10376528441063089,
            0.17090795287526034,
            0.21261268356748492,
            0.2402963749837852,
            0.2724177041628385
          ],
          "best_objective": 0.9818583179039123,
          "n_evaluations": 77,
          "time_improvement_pct": 1.8141682096087717
        },
        "Bayesiano": {
          "weights": [
            0.2913566054762269,
            0.041012497102193526,
            0.333030978835549,
            0.09018561518129001,
            0.24441430340474057
          ],
          "best_objective": 0.9862880094594495,
          "n_evaluations": 40,
          "time_improvement_pct": 1.3711990540550498
        }
      },
      "greedy_vs_jv": {
        "time_saving_pct": -0.0920553605957916,
        "p_value_time": 0.8608820719089015
      },
      "figures": {
        "base_vs_improved": "results\\study_v2\\massive_ops\\base_vs_improved.png",
        "convergence": "results\\study_v2\\massive_ops\\convergence_3tuners.png",
        "weights": "results\\study_v2\\massive_ops\\weights5.png",
        "test_improvement": "results\\study_v2\\massive_ops\\test_improvement.png",
        "greedy_vs_jv": "results\\study_v2\\massive_ops\\greedy_vs_jv.png"
      }
    }
  ],
  "milp_comparison": {
    "milp_makespan": 894.57143,
    "jv_makespan": 1089.142857142857,
    "gap_pct": 21.75023934565596,
    "n_drones": 5,
    "n_orders": 10,
    "figure": "results\\study_v2\\milp_gap.png"
  }
}